DiscSelfEasy/__init__.py
DiscSelfEasy/main.py
DiscSelfEasy-0.4.dist-info/METADATA
DiscSelfEasy-0.4.dist-info/WHEEL
DiscSelfEasy-0.4.dist-info/top_level.txt
DiscSelfEasy-0.4.dist-info/RECORD
